CHANGES.rst
LICENSE.GPL
LICENSE.rst
MANIFEST.in
README.rst
constraints.txt
requirements.txt
setup.cfg
setup.py
tox.ini
bobtemplates/__init__.py
bobtemplates.cs.egg-info/PKG-INFO
bobtemplates.cs.egg-info/SOURCES.txt
bobtemplates.cs.egg-info/dependency_links.txt
bobtemplates.cs.egg-info/entry_points.txt
bobtemplates.cs.egg-info/namespace_packages.txt
bobtemplates.cs.egg-info/not-zip-safe
bobtemplates.cs.egg-info/requires.txt
bobtemplates.cs.egg-info/top_level.txt
bobtemplates/cs/__init__.py
bobtemplates/cs/base.py
bobtemplates/cs/bobregistry.py
bobtemplates/cs/buildout.py
bobtemplates/cs/buildout_plone_volto.py
bobtemplates/cs/migration.py
bobtemplates/cs/cs_migration/.mrbob.ini
bobtemplates/cs/cs_migration/migration/README.rst.bob
bobtemplates/cs/cs_migration/migration/__init__.py
bobtemplates/cs/cs_migration/migration/configure.zcml
bobtemplates/cs/cs_migration/migration/blueprints/__init__.py
bobtemplates/cs/cs_migration/migration/blueprints/configure.zcml.bob
bobtemplates/cs/cs_migration/migration/blueprints/pytz_fixer.py
bobtemplates/cs/cs_migration/migration/blueprints/reference_fields.py
bobtemplates/cs/cs_migration/migration/blueprints/user_and_group_import.py
bobtemplates/cs/cs_migration/migration/pipelines/__init__.py
bobtemplates/cs/cs_migration/migration/pipelines/configure.zcml.bob
bobtemplates/cs/cs_migration/migration/pipelines/migration1.cfg.bob
bobtemplates/cs/cs_migration/migration/scripts/__init__.py
bobtemplates/cs/cs_migration/migration/scripts/export_users_and_groups.py
bobtemplates/cs/cs_migration/migration/scripts/list_migrations.py.bob
bobtemplates/cs/cs_migration/migration/scripts/run_migration.py
bobtemplates/cs/cs_plone_buildout/.gitignore
bobtemplates/cs/cs_plone_buildout/.mrbob.ini
bobtemplates/cs/cs_plone_buildout/README.rst.bob
bobtemplates/cs/cs_plone_buildout/buildout.cfg.bob
bobtemplates/cs/cs_plone_buildout/deployment.cfg
bobtemplates/cs/cs_plone_buildout/haproxy.cfg.bob
bobtemplates/cs/cs_plone_buildout/plone.yml
bobtemplates/cs/cs_plone_buildout/requirements.txt
bobtemplates/cs/cs_plone_buildout/services.cfg
bobtemplates/cs/cs_plone_buildout/varnish.cfg.bob
bobtemplates/cs/cs_plone_buildout/webserver.cfg
bobtemplates/cs/cs_plone_buildout/.vscode/launch.json
bobtemplates/cs/cs_plone_buildout/etc/.gitkeep
