Metadata-Version: 2.1
Name: bobtemplates.cs
Version: 1.9.1
Summary: Templates for Plone projects by CodeSyntax
Home-page: https://github.com/codesyntax/bobtemplates.cs
Author: Mikel Larreategi
Author-email: mlarreategi@codesyntax.com
License: GPLv2
Keywords: web plone zope skeleton project
Classifier: Environment :: Console
Classifier: Intended Audience :: Developers
Classifier: Natural Language :: English
Classifier: Operating System :: OS Independent
Classifier: Programming Language :: Python
Classifier: Programming Language :: Python :: 2.7
Classifier: Programming Language :: Python :: 3.4
Classifier: Programming Language :: Python :: 3.5
Classifier: Programming Language :: Python :: 3.6
Classifier: Programming Language :: Python :: Implementation :: CPython
Classifier: Development Status :: 5 - Production/Stable
Classifier: Topic :: Software Development :: Code Generators
Classifier: Topic :: Utilities
Classifier: License :: OSI Approved :: GNU General Public License v2 (GPLv2)
License-File: LICENSE.GPL
License-File: LICENSE.rst
Requires-Dist: setuptools
Requires-Dist: mr.bob
Requires-Dist: bobtemplates.plone
Requires-Dist: lxml
Requires-Dist: stringcase
